{
  "checkout": null,
  "commit": "045032abff91d495a48deb62ad1954c99787a550",
  "context": {
    "cookiecutter": {
      "project_name": "Toolbox",
      "project_slug": "toolbox",
      "github_username": "lucasrcezimbra",
      "database": "SQLite",
      "api": "No",
      "html": "HTMX",
      "css": "Bootstrap",
      "deploy": "No",
      "use_sentry": false,
      "staticfiles": true,
      "_template": "https://github.com/lucasrcezimbra/django-template",
      "_commit": "045032abff91d495a48deb62ad1954c99787a550"
    }
  },
  "directory": null,
  "template": "https://github.com/lucasrcezimbra/django-template"
}
